demo_app/__init__.py
demo_app/app.py
demo_app/config.py
demo_app/gunicorn.py
demo_app/test.http
demo_app/wsgi.py
demo_app/extensions/__init__.py
demo_app/extensions/logging/__init__.py
demo_app/extensions/unleash/__init__.py
demo_app/helpers/requestid.py
demo_app/modules/__init__.py
demo_app/modules/check/__init__.py
demo_app/modules/check/resources.py
flask_unleash/__init__.py
tests/__init__.py
tests/conftest.py
tests/test_helloworld.py
flask_unleash-2.1.0.dist-info/LICENSE
flask_unleash-2.1.0.dist-info/METADATA
flask_unleash-2.1.0.dist-info/WHEEL
flask_unleash-2.1.0.dist-info/top_level.txt
flask_unleash-2.1.0.dist-info/RECORD
