Metadata-Version: 2.1
Name: flask-unleash
Version: 2.1.0
Summary: Flask extension for unleash-client-python.
Home-page: https://github.com/Unleash/Flask-Unleash
Author: Ivan Lee
Author-email: ivanklee86@gmail.com
License: MIT
Platform: any
Classifier: Development Status :: 4 - Beta
Classifier: Intended Audience :: Developers
Classifier: License :: OSI Approved :: MIT License
Classifier: Programming Language :: Python :: 3.6
Classifier: Programming Language :: Python :: 3.7
Classifier: Programming Language :: Python :: 3.8
Classifier: Programming Language :: Python :: 3.9
Classifier: Programming Language :: Python :: 3.10
Requires-Dist: UnleashClient
Requires-Dist: Flask
